setup.py
phoenix_ml6/Framework.py
phoenix_ml6/__init__.py
phoenix_ml6.egg-info/PKG-INFO
phoenix_ml6.egg-info/SOURCES.txt
phoenix_ml6.egg-info/dependency_links.txt
phoenix_ml6.egg-info/not-zip-safe
phoenix_ml6.egg-info/top_level.txt